LICENSE.txt
MANIFEST.in
README
VERSION
contributors.txt
requirements.txt
setup.cfg
setup.py
scripts/.hgkeep
telejson/__init__.py
telejson_installer.egg-info/PKG-INFO
telejson_installer.egg-info/SOURCES.txt
telejson_installer.egg-info/dependency_links.txt
telejson_installer.egg-info/not-zip-safe
telejson_installer.egg-info/top_level.txt